calqtator/__init__.py
calqtator/__main__.py
calqtator/_calqtator.py
calqtator-0.2.0.dist-info/LICENSE
calqtator-0.2.0.dist-info/METADATA
calqtator-0.2.0.dist-info/WHEEL
calqtator-0.2.0.dist-info/entry_points.txt
calqtator-0.2.0.dist-info/top_level.txt
calqtator-0.2.0.dist-info/RECORD
