Metadata-Version: 2.1
Name: calqtator
Version: 0.2.0
Summary: A simple calculator widget PySide6.
Home-page: https://github.com/chrisimcevoy/calqtator
Author: Chris McEvoy
Author-email: chrisimcevoy@gmail.com
License: MIT
Platform: UNKNOWN
Requires-Dist: PySide6
